README.txt
setup.py
casexml/__init__.py
casexml.egg-info/PKG-INFO
casexml.egg-info/SOURCES.txt
casexml.egg-info/dependency_links.txt
casexml.egg-info/requires.txt
casexml.egg-info/top_level.txt
casexml/apps/__init__.py
casexml/apps/case/__init__.py
casexml/apps/case/const.py
casexml/apps/case/exceptions.py
casexml/apps/case/models.py
casexml/apps/case/sharedmodels.py
casexml/apps/case/signals.py
casexml/apps/case/util.py
casexml/apps/case/xform.py
casexml/apps/case/templatetags/__init__.py
casexml/apps/case/templatetags/case_tags.py
casexml/apps/case/tests/__init__.py
casexml/apps/case/tests/test_attachments.py
casexml/apps/case/tests/test_bugs.py
casexml/apps/case/tests/test_const.py
casexml/apps/case/tests/test_exclusion.py
casexml/apps/case/tests/test_force_save.py
casexml/apps/case/tests/test_from_xform.py
casexml/apps/case/tests/test_indexes.py
casexml/apps/case/tests/test_multi_case_submits.py
casexml/apps/case/tests/test_ota_restore.py
casexml/apps/case/tests/test_rebuild.py
casexml/apps/case/tests/test_v2_parsing.py
casexml/apps/case/tests/util.py
casexml/apps/case/xml/__init__.py
casexml/apps/case/xml/generator.py
casexml/apps/case/xml/parser.py
casexml/apps/phone/__init__.py
casexml/apps/phone/caselogic.py
casexml/apps/phone/checksum.py
casexml/apps/phone/fixtures.py
casexml/apps/phone/middleware.py
casexml/apps/phone/models.py
casexml/apps/phone/restore.py
casexml/apps/phone/signals.py
casexml/apps/phone/urls.py
casexml/apps/phone/views.py
casexml/apps/phone/xml.py
casexml/apps/phone/templatetags/__init__.py
casexml/apps/phone/templatetags/sync_log_tags.py
casexml/apps/phone/tests/__init__.py
casexml/apps/phone/tests/const.py
casexml/apps/phone/tests/dummy.py
casexml/apps/phone/tests/test_ota_restore.py
casexml/apps/phone/tests/test_state_hash.py
casexml/apps/phone/tests/test_sync_logs.py
casexml/apps/phone/tests/test_sync_mode.py