Metadata-Version: 1.0
Name: casexml
Version: 1.0.0
Summary: Dimagi CaseXML for Django
Home-page: http://www.dimagi.com/
Author: Dimagi
Author-email: dev@dimagi.com
License: UNKNOWN
Platform: UNKNOWN
